__init__.py
__main__.py
adapter.py
cli.py
discovery.py
manifest.py
registry.py
remote.py
tracking.py
validate.py
adapters/__init__.py
adapters/base.py
adapters/claude.py
adapters/codex.py
adapters/copilot.py
adapters/cursor.py
adapters/windsurf.py
agents/__init__.py
agents/base.py
agents/claude.py
agents/codex.py
agents/copilot.py
agents/opencode.py
agents/registry.py
commands/__init__.py
commands/adapter.py
commands/add.py
commands/clean.py
commands/clone.py
commands/config.py
commands/diff.py
commands/exec.py
commands/find.py
commands/help.py
commands/info.py
commands/list.py
commands/registry.py
commands/rm.py
commands/status.py
commands/sync.py
commands/update.py
commands/use.py
commands/validate.py
config/__init__.py
config/defaults.py
config/schema.py
skillcopy/__init__.py
skillcopy/local.py
skillcopy/remote.py
oasr-0.4.2.dist-info/METADATA
oasr-0.4.2.dist-info/WHEEL
oasr-0.4.2.dist-info/entry_points.txt
oasr-0.4.2.dist-info/licenses/LICENSE
oasr-0.4.2.dist-info/licenses/NOTICE
oasr-0.4.2.dist-info/RECORD
