Metadata-Version: 2.4
Name: oasr
Version: 0.4.2
Summary: CLI for managing agent skills across IDE integrations
Project-URL: Homepage, https://github.com/jgodau/asr
Project-URL: Repository, https://github.com/jgodau/asr
Project-URL: Changelog, https://github.com/jgodau/asr/blob/main/CHANGELOG.md
Author: Jordan Godau
License:                                  Apache License
License-File: LICENSE
License-File: NOTICE
Keywords: agents,automation,cli,ide,skills
Classifier: Development Status :: 4 - Beta
Classifier: Environment :: Console
Classifier: Intended Audience :: Developers
Classifier: License :: OSI Approved :: MIT License
Classifier: Programming Language :: Python :: 3
Classifier: Programming Language :: Python :: 3 :: Only
Classifier: Programming Language :: Python :: 3.10
Classifier: Programming Language :: Python :: 3.11
Classifier: Programming Language :: Python :: 3.12
Classifier: Programming Language :: Python :: 3.13
Classifier: Topic :: Software Development :: Build Tools
Classifier: Topic :: Software Development :: Libraries :: Application Frameworks
Requires-Python: >=3.10
Requires-Dist: pyyaml>=6.0
Requires-Dist: tomli-w>=1.0.0
Requires-Dist: tomli>=2.0.0; python_version < '3.11'
Provides-Extra: dev
Requires-Dist: pytest-cov; extra == 'dev'
Requires-Dist: pytest>=7.0; extra == 'dev'
